Workbook

Sheet Cover
B2: Apple
C11: Apple Inc. – DCF Valuation & Analysis
C13: Table of Contents | H13: Model Checks
C15: Summary | H15: Incorrect Date Set for Valuation? | M15: =Inputs!$F$107 -> 0
C16: Inputs | H16: Incorrect Date Set for First Cash Flow? | M16: =Inputs!$F$108 -> 0
C17: Model | H17: Terminal Growth Rate Greater Than or Equal To WACC? | M17: =Inputs!$F$119 -> 0
C18: DCF | H18: Model Exceeding Operational Capacity? | M18: =IF(SUM(Model!$F$179:$N$179)>0,1,0) -> 0
H19: Unused Tax Losses Remaining? (Levered Schedule) | M19: =Model!$D$366 -> 0
H20: Unused Tax Losses Remaining? (Unlevered Schedule) | M20: =Model!$D$408 -> 0
H21: Two UFCF Methods Different? | M21: =IF(SUM(Model!$AI$427:$AN$427)>0,1,0) -> 0

Sheet Summary_Sheet
C1: Apple
B3: Apple Inc. – DCF Valuation & Analysis
C5: This model provides a 5-year integrated forecast (2026–2030) for Apple Inc.
C6: It calculates intrinsic value using both Perpetuity Growth and Exit Multiple methods,
C7: with interactive sensitivity analysis hosted in Power BI.
C9: All figures in USD millions unless stated
B12: Current Stock Price | F12: =Inputs!F115 -> 258.87
B13: Implied Share Price (Perpetuity) | F13: =DCF!M82 -> 134.64814
B14: Implied Share Price (Exit Multiple) | F14: =DCF!M129 -> 207.81543
B15: WACC | F15: =Inputs!L76 -> 0.08564409
B16: Terminal Growth Rate | F16: =Inputs!F116 -> 0.025
B17: Terminal EBITDA Multiple | F17: =Inputs!F117 -> 22
B18: Blended Upside / (Downside) | F18: =AVERAGE(((F13-F12)/F12),(F14-F12)/F12) -> -0.33854141
D23: =HYPERLINK(LEFT(CELL("filename",A1),FIND("[",CELL("filename",A1))-1)&"Apple_dashboard.pbix","▶ View Power BI Dashboard") -> ▶ View Power BI Dashboard
B27: Summary
C29: Year | D29: UFCF | E29: Net Cash | F29: Shares Outstanding | I29: Year | J29: UFCF | K29: EBITDA | L29: Net Cash | M29: Shares Outstanding
C30: 2026 | D30: =DCF!I21 -> 112360.89 | E30: =-Inputs!$L$107 -> 54286 | F30: =Inputs!$F$114 -> 14776 | I30: 2026 | J30: =DCF!I31 -> 112360.89 | K30: =DCF!$N$98 -> 177027.97 | L30: =-Inputs!$L$107 -> 54286 | M30: =Inputs!$F$114 -> 14776
C31: 2027 | D31: =DCF!J21 -> 121173.02 | E31: =-Inputs!$L$107 -> 54286 | F31: =Inputs!$F$114 -> 14776 | I31: 2027 | J31: =DCF!J31 -> 121173.02 | K31: =DCF!$N$98 -> 177027.97 | L31: =-Inputs!$L$107 -> 54286 | M31: =Inputs!$F$114 -> 14776
C32: 2028 | D32: =DCF!K21 -> 125735.19 | E32: =-Inputs!$L$107 -> 54286 | F32: =Inputs!$F$114 -> 14776 | I32: 2028 | J32: =DCF!K31 -> 125735.19 | K32: =DCF!$N$98 -> 177027.97 | L32: =-Inputs!$L$107 -> 54286 | M32: =Inputs!$F$114 -> 14776
C33: 2029 | D33: =DCF!L21 -> 128851.36 | E33: =-Inputs!$L$107 -> 54286 | F33: =Inputs!$F$114 -> 14776 | I33: 2029 | J33: =DCF!L31 -> 128851.36 | K33: =DCF!$N$98 -> 177027.97 | L33: =-Inputs!$L$107 -> 54286 | M33: =Inputs!$F$114 -> 14776
C34: 2030 | D34: =DCF!M21 -> 131822.8 | E34: =-Inputs!$L$107 -> 54286 | F34: =Inputs!$F$114 -> 14776 | I34: 2030 | J34: =DCF!M31 -> 131822.8 | K34: =DCF!$N$98 -> 177027.97 | L34: =-Inputs!$L$107 -> 54286 | M34: =Inputs!$F$114 -> 14776
C35: term | D35: =DCF!N21 -> 130172.3 | E35: =-Inputs!$L$107 -> 54286 | F35: =Inputs!$F$114 -> 14776 | I35: term | J35: =DCF!N31 -> 130172.3 | K35: =DCF!$N$98 -> 177027.97 | L35: =-Inputs!$L$107 -> 54286 | M35: =Inputs!$F$114 -> 14776
B38: This integrated valuation hub bridges a 5-year 3-statement forecast with dynamic DCF modeling.
B39: The analysis indicates a significant valuation gap, with the current market price trading at a 33.9% premium to the fundamental intrinsic value.
B40: Interactive sensitivity analysis of WACC and Terminal Growth is available via the Power BI link above.

Sheet Inputs
B1: Apple
B3: Drivers
B5: All figures in USD millions unless stated | G5: =$F$106 -> 2026 | H5: =G5+1 -> 2027 | I5: =H5+1 -> 2028 | J5: =I5+1 -> 2029 | K5: =J5+1 -> 2030 | L5: Term
B7: Driver Switch | D7: 2
B10: Sales Volume Growth | G10: {=INDEX(G12:G14,$D$7)} -> 0.043 | H10: {=INDEX(H12:H14,$D$7)} -> 0.032 | I10: {=INDEX(I12:I14,$D$7)} -> 0.017 | J10: {=INDEX(J12:J14,$D$7)} -> 0.016 | K10: {=INDEX(K12:K14,$D$7)} -> 0.016 | L10: {=INDEX(L12:L14,$D$7)} -> 0.01
B12: Best Case | G12: 0.065 | H12: 0.055 | I12: 0.04 | J12: 0.035 | K12: 0.035 | L12: 0.03
B13: Base Case | G13: 0.043 | H13: 0.032 | I13: 0.017 | J13: 0.016 | K13: 0.016 | L13: 0.01
B14: Worst Case | G14: 0.01 | H14: 0 | I14: -0.015 | J14: -0.02 | K14: -0.02 | L14: 0
B17: Pricing Increases | G17: {=INDEX(G19:G21,$D$7)} -> 0.025 | H17: {=INDEX(H19:H21,$D$7)} -> 0.015 | I17: {=INDEX(I19:I21,$D$7)} -> 0.015 | J17: {=INDEX(J19:J21,$D$7)} -> 0.01 | K17: {=INDEX(K19:K21,$D$7)} -> 0.01 | L17: {=INDEX(L19:L21,$D$7)} -> 0.015
B19: =$B$12 -> Best Case | G19: 0.035 | H19: 0.025 | I19: 0.02 | J19: 0.02 | K19: 0.02 | L19: 0.02
B20: =$B$13 -> Base Case | G20: 0.025 | H20: 0.015 | I20: 0.015 | J20: 0.01 | K20: 0.01 | L20: 0.015
B21: =$B$14 -> Worst Case | G21: -0.01 | H21: 0 | I21: 0 | J21: -0.005 | K21: -0.01 | L21: 0.005
B24: Capital Expenditure | G24: {=INDEX(G26:G28,$D$7)} -> 14500 | H24: {=INDEX(H26:H28,$D$7)} -> 15200 | I24: {=INDEX(I26:I28,$D$7)} -> 15800 | J24: {=INDEX(J26:J28,$D$7)} -> 16500 | K24: {=INDEX(K26:K28,$D$7)} -> 17200 | L24: {=INDEX(L26:L28,$D$7)} -> 18500
B26: =$B$12 -> Best Case | G26: 16000 | H26: 17500 | I26: 18500 | J26: 20000 | K26: 22000 | L26: 23000
B27: =$B$13 -> Base Case | G27: 14500 | H27: 15200 | I27: 15800 | J27: 16500 | K27: 17200 | L27: 18500
B28: =$B$14 -> Worst Case | G28: 13500 | H28: 14000 | I28: 14500 | J28: 15000 | K28: 15500 | L28: 16000
B31: Inflation Rate | G31: 0.024 | H31: 0.025 | I31: 0.023 | J31: 0.022 | K31: 0.021 | L31: 0.02
B36: Weighted Average Cost of Capital
B38: All figures in USD millions unless stated
H40: Average | I40: Debt/ | J40: Debt/ | K40: Levered | L40: Unlevered
B41: Name | D41: Region | F41: Debt | G41: Equity | H41: Tax Rate 1 | I41: Equity | J41: Capital | K41: Beta 2 | L41: Beta 3
B43: Microsoft (MSFT) | D43: Europe | F43: 35430 | G43: 3010000 | H43: 0.186 | I43: =F43/G43 -> 0.011770764 | J43: =F43/(F43+G43) -> 0.011633825 | K43: 0.92 | L43: =K43/(1+(1-H43)*I43) -> 0.91126877
B44: Alphabet (GOOGL) | D44: Europe | F44: 46550 | G44: 3680000 | H44: 0.159 | I44: =F44/G44 -> 0.012649457 | J44: =F44/(F44+G44) -> 0.012491447 | K44: 1.08 | L44: =K44/(1+(1-H44)*I44) -> 1.0686317
B45: Amazon (AMZN) | D45: Europe | F45: 67200 | G45: 2300000 | H45: 0.19 | I45: =F45/G45 -> 0.029217391 | J45: =F45/(F45+G45) -> 0.028387969 | K45: 1.15 | L45: =K45/(1+(1-H45)*I45) -> 1.1234132
B46: Samsung (SMSN) | D46: Europe | F46: 13800 | G46: 580000 | H46: 0.254 | I46: =F46/G46 -> 0.023793103 | J46: =F46/(F46+G46) -> 0.023240148 | K46: 1.25 | L46: =K46/(1+(1-H46)*I46) -> 1.2281999
B47: Sony (SONY) | D47: Europe | F47: 24700 | G47: 124620 | H47: 0.235 | I47: =F47/G47 -> 0.19820254 | J47: =F47/(F47+G47) -> 0.16541656 | K47: 1.2 | L47: =K47/(1+(1-H47)*I47) -> 1.0420059
G49: Average | H49: =AVERAGE(H43:H47) -> 0.2048 | I49: =AVERAGE(I43:I47) -> 0.05512665 | J49: =AVERAGE(J43:J47) -> 0.048233989 | K49: =AVERAGE(K43:K47) -> 1.12 | L49: =AVERAGE(L43:L47) -> 1.0747039
G50: Median | H50: =MEDIAN(H43:H47) -> 0.19 | I50: =MEDIAN(I43:I47) -> 0.023793103 | J50: =MEDIAN(J43:J47) -> 0.023240148 | K50: =MEDIAN(K43:K47) -> 1.15 | L50: =MEDIAN(L43:L47) -> 1.0686317
B53: Risk Premium for Equity | H53: Cost of Equity
B55: Market Risk Premium | F55: 0.04 | H55: Risk Free Rate | L55: 0.043
B56: Average Unlevered Beta | F56: =$L$49 -> 1.0747039 | H56: Equity Risk Premium | L56: =F58 -> 0.044077041
B57: Levered Beta 4 | F57: =F56*(1+(1-L65)*F69) -> 1.101926 | H57: Country Risk Premium | L57: 0
B58: Equity Risk Premium | F58: =F55*F57 -> 0.044077041 | H58: Cost of Equity | L58: =SUM(L55:L57) -> 0.087077041
B62: Capital Structure | H62: Cost of Debt
E64: Current | F64: Target | H64: Pre-Tax Cost of Debt | L64: 0.048
B65: Total Debt | D65: 106620 | E65: =D65/$D$67 -> 0.031764096 | F65: 0.03 | H65: Tax Rate | L65: 0.181
B66: Market Capitalization | D66: 3250000 | E66: =D66/$D$67 -> 0.9682359 | F66: =1-F65 -> 0.97 | H66: After-Tax Cost of Debt | L66: =L64*(1-L65) -> 0.039312
B67: Total Capitalization | D67: =SUM(D65:D66) -> 3356620 | E67: =SUM(E65:E66) -> 1 | F67: =SUM(F65:F66) -> 1
B69: Debt / Equity | E69: =E65/E66 -> 0.032806154 | F69: =F65/F66 -> 0.030927835 | H69: Weighted Average Cost of Capital
K71: Weight | L71: Cost
B72: Tax Rate is a 5-Year Average. | H72: Debt Capital | K72: =F65 -> 0.03 | L72: =L66 -> 0.039312
B73: Levered beta is based on 5-year monthly data. | H73: Equity Capital | K73: =F66 -> 0.97 | L73: =L58 -> 0.087077041
B74: Unlevered Beta = Levered Beta / (1 + (1 - Tax Rate) × Debt-to-Equity)
B75: Levered Beta = Unlevered Beta x (1 + (1 - Tax rate) x (Debt-to-Equity))
H76: Weighted Average Cost of Capital | L76: =SUMPRODUCT(K72:K73,L72:L73) -> 0.08564409
B80: Other Inputs
B82: All figures in USD millions unless stated | G82: =$F$106 -> 2026 | H82: =G82+1 -> 2027 | I82: =H82+1 -> 2028 | J82: =I82+1 -> 2029 | K82: =J82+1 -> 2030 | L82: Term
B85: Working Capital 1
B86: Accounts Receivable | E86: (Days) | G86: 35 | H86: 35 | I86: 35 | J86: 35 | K86: 35 | L86: =K86 -> 35
B87: Vendor Days | E87: (Days) | G87: 30 | H87: 30 | I87: 30 | J87: 30 | K87: 30 | L87: =K87 -> 30
B88: Inventory | E88: (Days) | G88: 10 | H88: 10 | I88: 10 | J88: 10 | K88: 10 | L88: =K88 -> 10
B89: Accounts Payable | E89: (Days) | G89: 115 | H89: 115 | I89: 115 | J89: 115 | K89: 115 | L89: =K89 -> 115
B92: Other Annual Inputs
B93: Inflation Rate | G93: 0.026 | H93: 0.024 | I93: 0.023 | J93: 0.022 | K93: 0.021 | L93: 0.02
B94: Term Debt | E94: Increase / (Decrease) | G94: -2500 | H94: -2000 | I94: -1500 | J94: -1000 | K94: -500 | L94: 0
B95: Common Equity | E95: Increase / (Decrease) | G95: -95000 | H95: -88000 | I95: -82000 | J95: -75000 | K95: 70000 | L95: 0
B96: Gross Margin % | G96: 0.462 | H96: 0.465 | I96: 0.469 | J96: 0.472 | K96: 0.476 | L96: 0.046
L99: We have assumed working capital amounts per day in terminal year are equal to the previous year.
B102: Dates | H102: =CONCATENATE("End of ",G5-1," Balances") -> End of 2025 Balances
B103: Valuation Date | E103: (YY-MM-DD) | F103: 46121 | H103: Tax Rate | L103: 0.158
B104: First Expected Cash Flow | E104: (YY-MM-DD) | F104: 46291 | H104: First Year Tax Depreciation | L104: 0.5
B105: First Fiscal Year End for Forecast | E105: (YY-MM-DD) | F105: 46291 | H105: Blended Tax Depreciation Rate | L105: 0.15
B106: First Year of Forecast | E106: (YYYY) | F106: =YEAR(F105) -> 2026 | H106: Tax Basis for Assets | K106: =CONCATENATE("(End of ",$H$5-1,")") -> (End of 2026) | L106: 114800
B107: Incorrect Date Set for Valuation? | F107: =IF(F103>F104,1,0) -> 0 | H107: Net Debt | L107: -54286
B108: Incorrect Date Set for First Cash Flow? | F108: =IF(F104>F105,1,0) -> 0 | H108: Property Plant & Equipment | L108: 49834
B109: Days in Period | F109: 365 | H109: Tax Basis for PP&E | L109: 34800
H110: Tax Losses | K110: =CONCATENATE("(End of ",$H$5-1,")") -> (End of 2026) | L110: 0
B113: Valuation | H113: Other Inputs
B114: Shares Outstanding | F114: 14776 | H114: Plant Capacity | K114: (Units/Day) | L114: 1600
B115: Current Stock Price | E115: (US$/sh) | F115: 258.87 | H115: Dividend Payout Ratio | L115: 0.145
B116: Terminal Growth Rate | F116: 0.025 | H116: R&D % of Revenue | L116: 0.085
B117: Terminal EBITDA Multiple 1 | F117: 22 | H117: Other Non-Op % of Revenue | L117: -0.001
B118: Weighted Average Cost of Capital (WACC) | F118: =L76 -> 0.08564409 | H118: Projected Interest Expense | L118: 2850
B119: Terminal Growth Greater Than or Equal To WACC? | F119: =IF(F116>=F118,1,0) -> 0 | H119: First Year Tax Depreciation | L119: 0.5
H120: Blended Tax Depreciation Rate | L120: 0.143
H121: Deferred revenue as % of revenue | L121: 0.021
B124: Interest Rates | H124: Depreciation
B125: Cash Balances | F125: 0.042 | H125: First Year Accounting Depreciation | L125: 0.5
B126: Long Term Debt | F126: 0.035 | H126: Useful Life: Existing Assets | K126: (Years) | L126: 5
H127: Useful Life: New Assets | K127: (Years) | L127: 7
M130: The Terminal EBITDA multiple should reflect a 'steady-state' industry multiple.

Sheet Model
B1: Apple
B3: Income Statement
B5: All figures in USD millions unless stated | F5: =F$141 -> 2023 | G5: =G$141 -> 2024 | H5: =H$141 -> 2025 | I5: =I$141 -> 2026 | J5: =J$141 -> 2027 | K5: =K$141 -> 2028 | L5: =L$141 -> 2029 | M5: =M$141 -> 2030 | N5: =N$141 -> Term
B6: =$B$142 -> Model Running: Base Case Drivers
B8: Inflation | F8: =F189 -> 0.034 | G8: =G189 -> 0.024 | H8: =H189 -> 0.023 | I8: =I189 -> 0.024 | J8: =J189 -> 0.025 | K8: =K189 -> 0.023 | L8: =L189 -> 0.022 | M8: =M189 -> 0.021 | N8: =N189 -> 0.02
B11: Tax Rate | C11: =Inputs!$L$65 -> 0.181
B13: Revenue | F13: 383285 | G13: 391035 | H13: 416161 | I13: =I176 -> 444907.41 | J13: =J176 -> 466031.62 | K13: =K176 -> 481063.47 | L13: =L176 -> 493648.09 | M13: =M176 -> 506561.92 | N13: =N176 -> 519301.95
B14: COGS | F14: -214137 | G14: -210352 | H14: -220960 | I14: =I225*-1 -> -235287.99 | J14: =J225*-1 -> -248350.18 | K14: =K225*-1 -> -258089.2 | L14: =L225*-1 -> -267706.47 | M14: =M225*-1 -> -277414.7 | N14: =N225*-1 -> -285609.75
B15: Gross Profit | F15: =SUM(F13:F14) -> 169148 | G15: =SUM(G13:G14) -> 180683 | H15: =SUM(H13:H14) -> 195201 | I15: =SUM(I13:I14) -> 209619.42 | J15: =SUM(J13:J14) -> 217681.44 | K15: =SUM(K13:K14) -> 222974.27 | L15: =SUM(L13:L14) -> 225941.61 | M15: =SUM(M13:M14) -> 229147.22 | N15: =SUM(N13:N14) -> 233692.2
B18: SG&A | F18: -24932 | G18: -26097 | H18: -27601 | I18: =H18*(1+I$8) -> -28263.424 | J18: =I18*(1+J$8) -> -28970.01 | K18: =J18*(1+K$8) -> -29636.32 | L18: =K18*(1+L$8) -> -30288.319 | M18: =L18*(1+M$8) -> -30924.374 | N18: =M18*(1+N$8) -> -31542.861
B19: R&D | F19: -29915 | G19: -31370 | H19: -34550 | I19: =-I13*Inputs!$L$116 -> -37817.13 | J19: =-J13*Inputs!$L$116 -> -39612.687 | K19: =-K13*Inputs!$L$116 -> -40890.395 | L19: =-L13*Inputs!$L$116 -> -41960.087 | M19: =-M13*Inputs!$L$116 -> -43057.763 | N19: =-N13*Inputs!$L$116 -> -44140.666
B20: Other | F20: 0 | G20: 0 | H20: 0 | I20: =-I13*Inputs!$L$117 -> 444.90741 | J20: =-J13*Inputs!$L$117 -> 466.03162 | K20: =-K13*Inputs!$L$117 -> 481.06347 | L20: =-L13*Inputs!$L$117 -> 493.64809 | M20: =-M13*Inputs!$L$117 -> 506.56192 | N20: =-N13*Inputs!$L$117 -> 519.30195
B22: Depreciation | F22: -11519 | G22: -11445 | H22: -11698 | I22: =-I319 -> -11002.514 | J22: =-J319 -> -13123.943 | K22: =-K319 -> -15338.229 | L22: =-L319 -> -17645.371 | M22: =-M319 -> -20052.514 | N22: =-Inputs!L24 -> -18500
B23: EBIT | F23: =SUM(F15:F20) -> 114301 | G23: =SUM(G15:G20) -> 123216 | H23: =SUM(H15:H20) -> 133050 | I23: =SUM(I15:I20) -> 143983.77 | J23: =SUM(J15:J20) -> 149564.77 | K23: =SUM(K15:K20) -> 152928.62 | L23: =SUM(L15:L20) -> 154186.85 | M23: =SUM(M15:M20) -> 155671.64 | N23: =SUM(N15:N20) -> 158527.97
B26: Interest Income | F26: 3750 | G26: 3921 | H26: 3744 | I26: =I454 -> 1518.6989 | J26: =J454 -> 1867.4504 | K26: =K454 -> 2560.0993 | L26: =L454 -> 3412.518 | M26: =M454 -> 4484.6858 | N26: =M26*(1+Inputs!$F$116) -> 4596.8029
B27: Interest Expense | F27: -3933 | G27: -3803 | H27: -3767 | I27: =-I500 -> -3421.834 | J27: =-J500 -> -3020.384 | K27: =-K500 -> -2653.159 | L27: =-L500 -> -2250.784 | M27: =-M500 -> -1885.409 | N27: =M27*(1+Inputs!$F$116) -> -1932.5442
B28: Other Income/(Expense) | F28: -382 | G28: 151 | H28: -298 | I28: -200 | J28: -200 | K28: -200 | L28: -200 | M28: -200 | N28: 0
B29: EBT | F29: =SUM(F23:F28) -> 113736 | G29: =SUM(G23:G28) -> 123485 | H29: =SUM(H23:H28) -> 132729 | I29: =SUM(I23:I28) -> 141880.64 | J29: =SUM(J23:J28) -> 148211.84 | K29: =SUM(K23:K28) -> 152635.56 | L29: =SUM(L23:L28) -> 155148.59 | M29: =SUM(M23:M28) -> 158070.92 | N29: =SUM(N23:N28) -> 161192.23
B31: Current Tax | F31: -17589 | G31: -32864 | H31: -18252 | I31: =-I389 -> -25282.104 | J31: =-J389 -> -26351.256 | K31: =-K389 -> -27071.792 | L31: =-L389 -> -27443.132 | M31: =-M389 -> -27884.935 | N31: =-C11*N29 -> -29175.794
B32: Deferred Tax | F32: 848 | G32: 3115 | H32: -2467 | I32: =-I390 -> -398.29102 | J32: =-J390 -> -475.08673 | K32: =-K390 -> -555.24387 | L32: =-L390 -> -638.76245 | M32: =-M390 -> -725.90102 | N32: 0
B33: Total Tax | F33: =SUM(F31:F32) -> -16741 | G33: =SUM(G31:G32) -> -29749 | H33: =SUM(H31:H32) -> -20719 | I33: =SUM(I31:I32) -> -25680.395 | J33: =SUM(J31:J32) -> -26826.343 | K33: =SUM(K31:K32) -> -27627.036 | L33: =SUM(L31:L32) -> -28081.894 | M33: =SUM(M31:M32) -> -28610.836 | N33: =SUM(N31:N32) -> -29175.794
B35: Net Income | F35: =F29+F33 -> 96995 | G35: =G29+G33 -> 93736 | H35: =H29+H33 -> 112010 | I35: =I29+I33 -> 116200.24 | J35: =J29+J33 -> 121385.5 | K35: =K29+K33 -> 125008.52 | L35: =L29+L33 -> 127066.69 | M35: =M29+M33 -> 129460.08 | N35: =N29+N33 -> 132016.44
B39: Cash Flow Statement
B41: All figures in USD millions unless stated | F41: =F$141 -> 2023 | G41: =G$141 -> 2024 | H41: =H$141 -> 2025 | I41: =I$141 -> 2026 | J41: =J$141 -> 2027 | K41: =K$141 -> 2028 | L41: =L$141 -> 2029 | M41: =M$141 -> 2030
B42: =$B$142 -> Model Running: Base Case Drivers
B45: CASH FROM OPERATING
B46: Net Income | F46: =F35 -> 96995 | G46: =G35 -> 93736 | H46: =H35 -> 112010 | I46: =I35 -> 116200.24 | J46: =J35 -> 121385.5 | K46: =K35 -> 125008.52 | L46: =L35 -> 127066.69 | M46: =M35 -> 129460.08
B47: Deferred Taxes | F47: =-F32 -> -848 | G47: =-G32 -> -3115 | H47: =-H32 -> 2467 | I47: =-I32 -> 398.29102 | J47: =-J32 -> 475.08673 | K47: =-K32 -> 555.24387 | L47: =-L32 -> 638.76245 | M47: =-M32 -> 725.90102
B48: Depreciation | F48: =-F22 -> 11519 | G48: =-G22 -> 11445 | H48: =-H22 -> 11698 | I48: =-I22 -> 11002.514 | J48: =-J22 -> 13123.943 | K48: =-K22 -> 15338.229 | L48: =-L22 -> 17645.371 | M48: =-M22 -> 20052.514
B49: Cash From Accounts Receivable | F49: -1688 | G49: -3788 | H49: -6682 | I49: =I266 -> -2885.3545 | J49: =J266 -> -2025.6086 | K49: =K266 -> -1441.4103 | L49: =L266 -> -1206.7444 | M49: =M266 -> -1238.3128
B50: Cash From Vendor Non-Trade Receivables | F50: -6245 | G50: -1356 | H50: -347 | I50: =I267 -> -3387.7325 | J50: =J267 -> -1736.2359 | K50: =K267 -> -1235.4945 | L50: =L267 -> -1034.3523 | M50: =M267 -> -1061.411
B51: Cash From Inventory | F51: -1618 | G51: -1046 | H51: 1400 | I51: =I268 -> -728.24643 | J51: =J268 -> -357.86805 | K51: =K268 -> -266.82241 | L51: =L268 -> -263.48704 | M51: =M268 -> -265.97887
B52: Cash From Other Current Assets | F52: 6528 | G52: =G269 -> 408 | H52: =H269 -> -298 | I52: =I269 -> -350.04 | J52: =J269 -> -373.376 | K52: =K269 -> -352.09357 | L52: =L269 -> -344.53121 | M52: =M269 -> -336.10586
B53: Cash From Other Non-Current Assets | F53: -10330 | G53: =G270 -> -10076 | H53: =H270 -> -8893 | I53: =I270 -> -2009.448 | J53: =J270 -> -2143.4112 | K53: =K270 -> -2021.2368 | L53: =L270 -> -1977.8241 | M53: =M270 -> -1929.4573
B54: Cash From Other Current Liabilities | F54: -2016 | G54: =G271 -> 19475 | H54: =H271 -> -11917 | I54: =I271 -> 1593.288 | J54: =J271 -> 1699.5072 | K54: =K271 -> 1602.6353 | L54: =L271 -> 1568.2135 | M54: =M271 -> 1529.8635
B55: Cash From Other Non-Current Liabilities | F55: 706 | G55: =G272 -> -845 | H55: =H272 -> -6806 | I55: =I272 -> 1033.08 | J55: =J272 -> 1101.952 | K55: =K272 -> 1039.1407 | L55: =L272 -> 1016.8218 | M55: =M272 -> 991.95589
B56: Cash From Accounts Payable | F56: -1889 | G56: 6020 | H56: 902 | I56: =I273 -> 4271.834 | J56: =J273 -> 4115.4825 | K56: =K273 -> 3068.4577 | L56: =L273 -> 3030.1009 | M56: =M273 -> 3058.757
B57: Cash from Deferred Revenue | F57: -291 | G57: =G111-F111 -> 188 | H57: =H111-G111 -> 806 | I57: =I111-H111 -> 288.05564 | J57: =J111-I111 -> 443.60828 | K57: =K111-J111 -> 315.66884 | L57: =L111-K111 -> 264.27703 | M57: =M111-L111 -> 271.19051
B58: Share-Based Compensation | F58: 10833 | G58: 11688 | H58: 12863 | I58: =I515 -> 15068.427 | J58: =J515 -> 15846.644 | K58: =K515 -> 16430.796 | L58: =L515 -> 16997.744 | M58: =M515 -> 17569.842
B59: Other Historical Adjustments | F59: 8887 | G59: -4480 | H59: 4279 | I59: 0 | J59: 0 | K59: 0 | L59: 0 | M59: 0
B60: Subtotal | F60: =SUM(F45:F59) -> 110543 | G60: =SUM(G46:G59) -> 118254 | H60: =SUM(H45:H59) -> 111482 | I60: =SUM(I45:I59) -> 140494.91 | J60: =SUM(J45:J59) -> 151555.22 | K60: =SUM(K45:K59) -> 158041.64 | L60: =SUM(L45:L59) -> 163401.05 | M60: =SUM(M45:M59) -> 168828.84
B63: CASH FROM INVESTING
B64: Capital Expenditure | F64: -10959 | G64: -9447 | H64: -12715 | I64: =-I332 -> -14500 | J64: =-J332 -> -15200 | K64: =-K332 -> -15800 | L64: =-L332 -> -16500 | M64: =-M332 -> -17200
B65: Purchases/Sales of Marketable Securities | F65: 20553 | G65: 13690 | H65: 29390 | I65: 0 | J65: 0 | K65: 0 | L65: 0 | M65: 0
B66: Subtotal | F66: =SUM(F64:F65) -> 9594 | G66: =SUM(G64:G65) -> 4243 | H66: =SUM(H64:H65) -> 16675 | I66: =SUM(I64:I65) -> -14500 | J66: =SUM(J64:J65) -> -15200 | K66: =SUM(K64:K65) -> -15800 | L66: =SUM(L64:L65) -> -16500 | M66: =SUM(M64:M65) -> -17200
B69: CASH FROM FINANCING
B70: Change in Long-Term Debt | F70: -6505 | G70: -9505 | H70: -5201 | I70: =I462 -> -12350 | J70: =J462 -> -9350 | K70: =K462 -> -10500 | L70: =L462 -> -11250 | M70: =M462 -> -8500
B71: Repurchase of Common Stock | F71: -77550 | G71: -91858 | H71: -91100 | I71: =I520 -> -90000 | J71: =J520 -> -90000 | K71: =K520 -> -90000 | L71: =L520 -> -90000 | M71: =M520 -> -90000
B72: Change in Commercial Paper | F72: -3997 | G72: -3990 | H72: -65 | I72: =I492 -> 0 | J72: =J492 -> 0 | K72: =K492 -> 0 | L72: =L492 -> 0 | M72: =M492 -> 0
B73: Change in Common Equity | F73: -10741 | G73: -2285 | H73: -10739 | I73: =I516 -> -4000 | J73: =J516 -> -4000 | K73: =K516 -> -4000 | L73: =L516 -> -4000 | M73: =M516 -> -4000
B74: Dividends | F74: -15025 | G74: -14881 | H74: -15061 | I74: =I531 -> -17430.036 | J74: =J531 -> -18207.824 | K74: =K531 -> -18751.278 | L74: =L531 -> -19060.004 | M74: =M531 -> -19419.012
B75: Subtotal | F75: =SUM(F70:F74) -> -113818 | G75: =SUM(G70:G74) -> -122519 | H75: =SUM(H70:H74) -> -122166 | I75: =SUM(I70:I74) -> -123780.04 | J75: =SUM(J70:J74) -> -121557.82 | K75: =SUM(K70:K74) -> -123251.28 | L75: =SUM(L70:L74) -> -124310 | M75: =SUM(M70:M74) -> -121919.01
B78: CASH BALANCE
B79: Beginning of the Year | F79: 23646 | G79: 29965 | H79: 29943 | I79: =H81 -> 35934 | J79: =I81 -> 38148.873 | K79: =J81 -> 52946.268 | L79: =K81 -> 71936.625 | M79: =L81 -> 94527.666
B80: Increase / (Decrease) | F80: =F75+F66+F60 -> 6319 | G80: =G75+G66+G60 -> -22 | H80: =H75+H66+H60 -> 5991 | I80: =I75+I66+I60 -> 2214.8731 | J80: =J75+J66+J60 -> 14797.395 | K80: =K75+K66+K60 -> 18990.357 | L80: =L75+L66+L60 -> 22591.041 | M80: =M75+M66+M60 -> 29709.829
B81: End of the Year | F81: =SUM(F79:F80) -> 29965 | G81: =SUM(G79:G80) -> 29943 | H81: =SUM(H79:H80) -> 35934 | I81: =SUM(I79:I80) -> 38148.873 | J81: =SUM(J79:J80) -> 52946.268 | K81: =SUM(K79:K80) -> 71936.625 | L81: =SUM(L79:L80) -> 94527.666 | M81: =SUM(M79:M80) -> 124237.49
B85: Balance Sheet
B87: All figures in USD millions unless stated | F87: =F$141 -> 2023 | G87: =G$141 -> 2024 | H87: =H$141 -> 2025 | I87: =I$141 -> 2026 | J87: =J$141 -> 2027 | K87: =K$141 -> 2028 | L87: =L$141 -> 2029 | M87: =M$141 -> 2030
B88: =$B$142 -> Model Running: Base Case Drivers
B90: ASSETS
B92: Cash | F92: 29965 | G92: 29943 | H92: 35934 | I92: =I81 -> 38148.873 | J92: =J81 -> 52946.268 | K92: =K81 -> 71936.625 | L92: =L81 -> 94527.666 | M92: =M81 -> 124237.49
B93: Current Marketable Securities | F93: 31590 | G93: 35228 | H93: 18763 | I93: =H93 -> 18763 | J93: =I93 -> 18763 | K93: =J93 -> 18763 | L93: =K93 -> 18763 | M93: =L93 -> 18763
B94: Accounts Receivable | F94: 29508 | G94: 33410 | H94: 39777 | I94: =I249 -> 42662.355 | J94: =J249 -> 44687.963 | K94: =K249 -> 46129.373 | L94: =L249 -> 47336.118 | M94: =M249 -> 48574.431
B95: Vendor Non-Trade Receivables | F95: 31477 | G95: 32833 | H95: 33180 | I95: =I250 -> 36567.732 | J95: =J250 -> 38303.968 | K95: =K250 -> 39539.463 | L95: =L250 -> 40573.815 | M95: =M250 -> 41635.226
B96: Inventories | F96: 6331 | G96: 7286 | H96: 5718 | I96: =I251 -> 6446.2464 | J96: =J251 -> 6804.1145 | K96: =K251 -> 7070.9369 | L96: =L251 -> 7334.4239 | M96: =M251 -> 7600.4028
B97: Other Current Assets | F97: 14695 | G97: 14287 | H97: 14585 | I97: =I252 -> 14935.04 | J97: =J252 -> 15308.416 | K97: =K252 -> 15660.51 | L97: =L252 -> 16005.041 | M97: =M252 -> 16341.147
B98: Total Current Assets | F98: =SUM(F92:F97) -> 143566 | G98: =SUM(G92:G97) -> 152987 | H98: =SUM(H92:H97) -> 147957 | I98: =SUM(I92:I97) -> 157523.25 | J98: =SUM(J92:J97) -> 176813.73 | K98: =SUM(K92:K97) -> 199099.91 | L98: =SUM(L92:L97) -> 224540.06 | M98: =SUM(M92:M97) -> 257151.7
B100: Non-Current Marketable Securities | F100: 100544 | G100: 91479 | H100: 77723 | I100: =H100 -> 77723 | J100: =I100 -> 77723 | K100: =J100 -> 77723 | L100: =K100 -> 77723 | M100: =L100 -> 77723
B101: Property Plant & Equipment | F101: 43715 | G101: 45680 | H101: 49834 | I101: =I342 -> 53331.486 | J101: =J342 -> 55407.543 | K101: =K342 -> 55869.314 | L101: =L342 -> 54723.943 | M101: =M342 -> 51871.429
B102: Other Non-Current Assets | F102: 64758 | G102: 74834 | H102: 83727 | I102: =I253 -> 85736.448 | J102: =J253 -> 87879.859 | K102: =K253 -> 89901.096 | L102: =L253 -> 91878.92 | M102: =M253 -> 93808.377
B104: Total Assets | F104: =SUM(F98:F102) -> 352583 | G104: =SUM(G98:G102) -> 364980 | H104: =SUM(H98:H102) -> 359241 | I104: =SUM(I98:I102) -> 374314.18 | J104: =SUM(J98:J102) -> 397824.13 | K104: =SUM(K98:K102) -> 422593.32 | L104: =SUM(L98:L102) -> 448865.93 | M104: =SUM(M98:M102) -> 480554.51
B107: LIABILITIES
B109: Accounts Payable | F109: 62611 | G109: 68960 | H109: 69860 | I109: =I256 -> 74131.834 | J109: =J256 -> 78247.316 | K109: =K256 -> 81315.774 | L109: =L256 -> 84345.875 | M109: =M256 -> 87404.632
B110: Commercial Paper | F110: 5985 | G110: 9967 | H110: 7979 | I110: =I493 -> 7979 | J110: =J493 -> 7979 | K110: =K493 -> 7979 | L110: =L493 -> 7979 | M110: =M493 -> 7979
B111: Deferred revenue | F111: 8061 | G111: 8249 | H111: 9055 | I111: =I13*Inputs!$L$121 -> 9343.0556 | J111: =J13*Inputs!$L$121 -> 9786.6639 | K111: =K13*Inputs!$L$121 -> 10102.333 | L111: =L13*Inputs!$L$121 -> 10366.61 | M111: =M13*Inputs!$L$121 -> 10637.8
B112: Current Term Debt | F112: 9822 | G112: 10912 | H112: 12350 | I112: =-J462 -> 9350 | J112: =-K462 -> 10500 | K112: =-L462 -> 11250 | L112: =-M462 -> 8500 | M112: =-N462 -> 0
B113: Other Current Liabilities | F113: 58829 | G113: 78304 | H113: 66387 | I113: =I254 -> 67980.288 | J113: =J254 -> 69679.795 | K113: =K254 -> 71282.43 | L113: =L254 -> 72850.644 | M113: =M254 -> 74380.507
B114: Deferred Tax Liability | F114: =E114+F47 -> -848 | G114: =F114+G47 -> -3963 | H114: =G114+H47 -> -1496 | I114: =H114+I47 -> -1097.709 | J114: =I114+J47 -> -622.62225 | K114: =J114+K47 -> -67.378377 | L114: =K114+L47 -> 571.38407 | M114: =L114+M47 -> 1297.2851
B115: Total Current Liabilities | F115: =SUM(F109:F114) -> 144460 | G115: =SUM(G109:G114) -> 172429 | H115: =SUM(H109:H114) -> 164135 | I115: =SUM(I109:I114) -> 167686.47 | J115: =SUM(J109:J114) -> 175570.15 | K115: =SUM(K109:K114) -> 181862.16 | L115: =SUM(L109:L114) -> 184613.51 | M115: =SUM(M109:M114) -> 181699.22
B117: Term debt | F117: 95281 | G117: 85750 | H117: 78328 | I117: =I463-I112 -> 68978 | J117: =J463-J112 -> 58478 | K117: =K463-K112 -> 47228 | L117: =L463-L112 -> 38728 | M117: =M463-M112 -> 38728
B118: Other Non-Current Liabilities | F118: 50696 | G118: 49851 | H118: 43045 | I118: =I255 -> 44078.08 | J118: =J255 -> 45180.032 | K118: =K255 -> 46219.173 | L118: =L255 -> 47235.995 | M118: =M255 -> 48227.95
B119: Total Liabilities | F119: =SUM(F115:F118) -> 290437 | G119: =SUM(G115:G118) -> 308030 | H119: =SUM(H115:H118) -> 285508 | I119: =SUM(I115:I118) -> 280742.55 | J119: =SUM(J115:J118) -> 279228.19 | K119: =SUM(K115:K118) -> 275309.33 | L119: =SUM(L115:L118) -> 270577.51 | M119: =SUM(M115:M118) -> 268655.18
B122: EQUITY
B124: Common Equity | F124: 73812 | G124: 83276 | H124: 93568 | I124: =I517 -> 104636.43 | J124: =J517 -> 116483.07 | K124: =K517 -> 128913.87 | L124: =L517 -> 141911.61 | M124: =M517 -> 155481.45
B125: Retained Earnings | F125: 0 | G125: 0 | H125: 0 | I125: 0 | J125: 0 | K125: 0 | L125: 0 | M125: 0
B126: Accumulated deficit | F126: -214 | G126: -19154 | H126: -14264 | I126: =I533 -> -5493.7959 | J126: =J533 -> 7683.8752 | K126: =K533 -> 23941.119 | L126: =L533 -> 41947.808 | M126: =M533 -> 61988.879
B127: Accum Other Comprehensive Income/(Loss) | F127: -11452 | G127: -7172 | H127: -5571 | I127: -5571 | J127: -5571 | K127: -5571 | L127: -5571 | M127: -5571
B128: Total Shareholders' Equity | F128: =SUM(F124:F127) -> 62146 | G128: =SUM(G124:G127) -> 56950 | H128: =SUM(H124:H127) -> 73733 | I128: =SUM(I124:I127) -> 93571.632 | J128: =SUM(J124:J127) -> 118595.95 | K128: =SUM(K124:K127) -> 147283.99 | L128: =SUM(L124:L127) -> 178288.42 | M128: =SUM(M124:M127) -> 211899.33
B131: Total Liabilities & Equity | F131: =F128+F119 -> 352583 | G131: =G128+G119 -> 364980 | H131: =H128+H119 -> 359241 | I131: =I128+I119 -> 374314.18 | J131: =J128+J119 -> 397824.13 | K131: =K128+K119 -> 422593.32 | L131: =L128+L119 -> 448865.93 | M131: =M128+M119 -> 480554.51
B134: Check | F134: =ROUND(F131-F104,0) -> 0 | G134: =ROUND(G131-G104,0) -> 0 | H134: =ROUND(H131-H104,0) -> 0 | I134: =ROUND(I131-I104,0) -> 0 | J134: =ROUND(J131-J104,0) -> 0 | K134: =ROUND(K131-K104,0) -> 0 | L134: =ROUND(L131-L104,0) -> 0 | M134: =ROUND(M131-M104,0) -> 0
B139: Revenue Schedule
B141: All figures in USD millions unless stated | F141: =G141-1 -> 2023 | G141: =H141-1 -> 2024 | H141: =I141-1 -> 2025 | I141: =Inputs!$F$106 -> 2026 | J141: =I141+1 -> 2027 | K141: =J141+1 -> 2028 | L141: =K141+1 -> 2029 | M141: =L141+1 -> 2030 | N141: Term
B142: {=CONCATENATE("Model Running: ",INDEX(Inputs!$B$12:$B$14,Inputs!$D$7)," Drivers")} -> Model Running: Base Case Drivers
B144: Days in Period | C144: =Inputs!$F$109 -> 365 | F144: 365 | G144: 365 | H144: 365 | I144: =$C$144 -> 365 | J144: =$C$144 -> 365 | K144: =$C$144 -> 365 | L144: =$C$144 -> 365 | M144: =$C$144 -> 365 | N144: =$C$144 -> 365
B145: Plant Capacity | C145: =Inputs!$L$114 -> 1600
B148: OPERATIONS
B150: Sales Volume Growth | G150: =G152/F152-1 -> 0.036996539 | H150: =H152/G152-1 -> 0.10044712 | I150: =Inputs!G10 -> 0.043 | J150: =Inputs!H10 -> 0.032 | K150: =Inputs!I10 -> 0.017 | L150: =Inputs!J10 -> 0.016 | M150: =Inputs!K10 -> 0.016 | N150: =Inputs!L10 -> 0.01
B152: Sales Volume | D152: (Units/Day) | F152: 1061.775 | G152: 1101.057 | H152: 1211.655 | I152: =H152*(1+I150) -> 1263.7562 | J152: =I152*(1+J150) -> 1304.1964 | K152: =J152*(1+K150) -> 1326.3677 | L152: =K152*(1+L150) -> 1347.5896 | M152: =L152*(1+M150) -> 1369.151 | N152: =M152*(1+N150) -> 1382.8425
B153: Plant Capacity | D153: (Units/Day) | F153: 1350 | G153: 1420 | H153: 1550 | I153: =$C$145 -> 1600 | J153: =$C$145 -> 1600 | K153: =$C$145 -> 1600 | L153: =$C$145 -> 1600 | M153: =$C$145 -> 1600 | N153: =$C$145 -> 1600
B154: Operational Efficiency | F154: =F152/F153 -> 0.7865 | G154: =G152/G153 -> 0.77539225 | H154: =H152/H153 -> 0.7817129 | I154: =I152/I153 -> 0.7898476 | J154: =J152/J153 -> 0.81512273 | K154: =K152/K153 -> 0.82897981 | L154: =L152/L153 -> 0.84224349 | M154: =M152/M153 -> 0.85571939 | N154: =N152/N153 -> 0.86427658
...

Sheet DCF
B1: Apple
B3: Unlevered Free Cash Flow Schedule
B5: All figures in USD millions unless stated | I5: =Model!I5:N5 -> 2026 | J5: =Model!J5:O5 -> 2027 | K5: =Model!K5:P5 -> 2028 | L5: =Model!L5:Q5 -> 2029 | M5: =Model!M5:R5 -> 2030 | N5: =Model!N5:S5 -> Term
B6: =Model!$B$6 -> Model Running: Base Case Drivers
B8: TAX SHIELD FROM INTEREST | F8: Line Item | G8: Term
B9: Current Taxes (Unlevered) | F9: EBIT | G9: =Model!N23 -> 158527.97 | I9: =Model!I431 -> 25662.771 | J9: =Model!J431 -> 26596.137 | K9: =Model!K431 -> 27124.836 | L9: =Model!L431 -> 27269.058 | M9: =Model!M431 -> 27450.666 | N9: =G9*$G$11 -> 28693.563
B10: Current Taxes (Levered) | F10: EBT | G10: =Model!N29 -> 161192.23 | I10: =Model!I389 -> 25282.104 | J10: =Model!J389 -> 26351.256 | K10: =Model!K389 -> 27071.792 | L10: =Model!L389 -> 27443.132 | M10: =Model!M389 -> 27884.935 | N10: =G10*$G$11 -> 29175.794
B11: Total Tax Shield | F11: Tax Rate | G11: =Model!$C$11 -> 0.181 | I11: =I9-I10 -> 380.66745 | J11: =J9-J10 -> 244.88098 | K11: =K9-K10 -> 53.043807 | L11: =L9-L10 -> -174.07385 | M11: =M9-M10 -> -434.2691 | N11: =N9-N10 -> -482.23083
B16: EBITDA METHOD
B17: EBITDA | I17: =Model!I23+(-Model!I22) -> 154986.28 | J17: =Model!J23+(-Model!J22) -> 162688.71 | K17: =Model!K23+(-Model!K22) -> 168266.85 | L17: =Model!L23+(-Model!L22) -> 171832.23 | M17: =Model!M23+(-Model!M22) -> 175724.16 | N17: =Model!N23+(-Model!N22) -> 177027.97
B18: Current Taxes | I18: =-I9 -> -25662.771 | J18: =-J9 -> -26596.137 | K18: =-K9 -> -27124.836 | L18: =-L9 -> -27269.058 | M18: =-M9 -> -27450.666 | N18: =-N9 -> -28693.563
B19: Capital Expenditure | I19: =-Inputs!G24 -> -14500 | J19: =-Inputs!H24 -> -15200 | K19: =-Inputs!I24 -> -15800 | L19: =-Inputs!J24 -> -16500 | M19: =-Inputs!K24 -> -17200 | N19: =-Inputs!L24 -> -18500
B20: Change in Working Capital | I20: =Model!I274 -> -2462.6195 | J20: =Model!J274 -> 280.44197 | K20: =Model!K274 -> 393.17628 | L20: =Model!L274 -> 788.19707 | M20: =Model!M274 -> 749.31049 | N20: =Model!N274 -> 337.88612
B21: Unlevered Free Cash Flow | I21: =SUM(I17:I20) -> 112360.89 | J21: =SUM(J17:J20) -> 121173.02 | K21: =SUM(K17:K20) -> 125735.19 | L21: =SUM(L17:L20) -> 128851.36 | M21: =SUM(M17:M20) -> 131822.8 | N21: =SUM(N17:N20) -> 130172.3
B24: NET INCOME METHOD
B25: Net Income | I25: =Model!I35 -> 116200.24 | J25: =Model!J35 -> 121385.5 | K25: =Model!K35 -> 125008.52 | L25: =Model!L35 -> 127066.69 | M25: =Model!M35 -> 129460.08 | N25: =Model!N35 -> 132016.44
B26: Depreciation 1 | I26: =-Model!I22 -> 11002.514 | J26: =-Model!J22 -> 13123.943 | K26: =-Model!K22 -> 15338.229 | L26: =-Model!L22 -> 17645.371 | M26: =-Model!M22 -> 20052.514 | N26: =-Model!N22 -> 18500 | Z26: NET INCOME METHOD
B27: Deferred Tax 2 | I27: =-Model!I32 -> 398.29102 | J27: =-Model!J32 -> 475.08673 | K27: =-Model!K32 -> 555.24387 | L27: =-Model!L32 -> 638.76245 | M27: =-Model!M32 -> 725.90102 | N27: =-Model!N32 -> 0 | Z27: Net Income
B28: After-Tax Net Non-Operating Expense | C28: ` | I28: =((-Model!I27)-Model!I28-Model!I26)*(1-DCF!$G$11) -> 1722.4676 | J28: =((-Model!J27)-Model!J28-Model!J26)*(1-DCF!$G$11) -> 1108.0526 | K28: =((-Model!K27)-Model!K28-Model!K26)*(1-DCF!$G$11) -> 240.0159 | L28: =((-Model!L27)-Model!L28-Model!L26)*(1-DCF!$G$11) -> -787.66011 | M28: =((-Model!M27)-Model!M28-Model!M26)*(1-DCF!$G$11) -> -1965.0077 | N28: =((-Model!N27)-Model!N28-Model!N26)*(1-DCF!$G$11) -> -2182.0279 | Z28: Depreciation 1
B29: Capital Expenditure | I29: =I19 -> -14500 | J29: =J19 -> -15200 | K29: =K19 -> -15800 | L29: =L19 -> -16500 | M29: =M19 -> -17200 | N29: =N19 -> -18500 | Z29: Deferred Tax 2
B30: Change in Working Capital | I30: =I20 -> -2462.6195 | J30: =J20 -> 280.44197 | K30: =K20 -> 393.17628 | L30: =L20 -> 788.19707 | M30: =M20 -> 749.31049 | N30: =N20 -> 337.88612 | Z30: Interest Expense
B31: Unlevered Free Cash Flow | I31: =SUM(I25:I30) -> 112360.89 | J31: =SUM(J25:J30) -> 121173.02 | K31: =SUM(K25:K30) -> 125735.19 | L31: =SUM(L25:L30) -> 128851.36 | M31: =SUM(M25:M30) -> 131822.8 | N31: =SUM(N25:N30) -> 130172.3 | Z31: Less: Interest Income
Z32: Plus: Other Expense
Z33: Tax Shield From Interest
B34: Two UFCF Methods Different? | I34: =IF(ROUND(I21-I31,1)=0,0,1) -> 0 | J34: =IF(ROUND(J21-J31,1)=0,0,1) -> 0 | K34: =IF(ROUND(K21-K31,1)=0,0,1) -> 0 | L34: =IF(ROUND(L21-L31,1)=0,0,1) -> 0 | M34: =IF(ROUND(M21-M31,1)=0,0,1) -> 0 | N34: =IF(ROUND(N21-N31,1)=0,0,1) -> 0 | Z34: Capital Expenditure
Z35: Change in Working Capital
Z36: Unlevered Free Cash Flow
N37: Capital expenditure has been set equal to depreciation in the terminal year.
N38: This schedule assumes no deferred taxes in the terminal year.
B42: Discounted Cash Flow Schedule: Perpetuity Method
B44: All figures in USD millions unless stated
B45: =B6 -> Model Running: Base Case Drivers | H45: Valuation | I45: Discrete Forecast | N45: Term
H46: (YY-MM-DD) | I46: (YY-MM-DD) | J46: (YY-MM-DD) | K46: (YY-MM-DD) | L46: (YY-MM-DD) | M46: (YY-MM-DD) | N46: (YY-MM-DD)
B47: Terminal Growth | C47: =Inputs!F116 -> 0.025 | F47: Fiscal Year End | H47: =Inputs!F103 -> 46121 | I47: =Inputs!F105 -> 46291 | J47: =EDATE(I47,12) -> 46656 | K47: =EDATE(J47,12) -> 47022 | L47: =EDATE(K47,12) -> 47387 | M47: =EDATE(L47,12) -> 47752 | N47: =EDATE(M47,12) -> 48117
B48: WACC | C48: =Inputs!L76 -> 0.08564409 | F48: Cash Flow Timing | H48: =H47 -> 46121 | I48: =Inputs!F104 -> 46291 | J48: =EDATE(I48,12) -> 46656 | K48: =EDATE(J48,12) -> 47022 | L48: =EDATE(K48,12) -> 47387 | M48: =EDATE(L48,12) -> 47752 | N48: =EDATE(M48,12) -> 48117
B50: Unlevered Free Cash Flow | H50: 0 | I50: =I$31 -> 112360.89 | J50: =J$31 -> 121173.02 | K50: =K$31 -> 125735.19 | L50: =L$31 -> 128851.36 | M50: =M$31 -> 131822.8 | N50: =N$31 -> 130172.3
B53: UNADJUSTED CASH FLOW
B54: Discrete Forecast | H54: 0 | I54: =I50 -> 112360.89 | J54: =J50 -> 121173.02 | K54: =K50 -> 125735.19 | L54: =L50 -> 128851.36 | M54: =M50 -> 131822.8
B55: Terminal Value | H55: 0 | I55: 0 | J55: 0 | K55: 0 | L55: 0 | M55: =N50/(C48-C47) -> 2146496
B56: Total Cash Flow | H56: =SUM(H54:H55) -> 0 | I56: =SUM(I54:I55) -> 112360.89 | J56: =SUM(J54:J55) -> 121173.02 | K56: =SUM(K54:K55) -> 125735.19 | L56: =SUM(L54:L55) -> 128851.36 | M56: =SUM(M54:M55) -> 2278318.8
B58: ADJUSTED CASH FLOW
B59: Partial Period Adjustment | H59: 0 | I59: =YEARFRAC(I47,H47) -> 0.46388889 | J59: =YEARFRAC(J47,I47) -> 1 | K59: =YEARFRAC(K47,J47) -> 1 | L59: =YEARFRAC(L47,K47) -> 1 | M59: =YEARFRAC(M47,L47) -> 1
B61: Discrete Forecast | H61: 0 | I61: =I54*I$59 -> 52122.97 | J61: =J54*J$59 -> 121173.02 | K61: =K54*K$59 -> 125735.19 | L61: =L54*L$59 -> 128851.36 | M61: =M54*M$59 -> 131822.8
B62: Terminal Value | H62: 0 | I62: =I55*I$59 -> 0 | J62: =J55*J$59 -> 0 | K62: =K55*K$59 -> 0 | L62: =L55*L$59 -> 0 | M62: =M55*M$59 -> 2146496
B63: Total Cash Flow | H63: =SUM(H61:H62) -> 0 | I63: =SUM(I61:I62) -> 52122.97 | J63: =SUM(J61:J62) -> 121173.02 | K63: =SUM(K61:K62) -> 125735.19 | L63: =SUM(L61:L62) -> 128851.36 | M63: =SUM(M61:M62) -> 2278318.8
B65: DISCOUNTED CASH FLOW
B66: Years for Discounting | H66: 0 | I66: =H66+YEARFRAC(H48,I48) -> 0.46388889 | J66: =I66+YEARFRAC(I48,J48) -> 1.4638889 | K66: =J66+YEARFRAC(J48,K48) -> 2.4638889 | L66: =K66+YEARFRAC(K48,L48) -> 3.4638889 | M66: =L66+YEARFRAC(L48,M48) -> 4.4638889
B68: Discrete Forecast | H68: 0 | I68: =I61/(1+$C$48)^I$66 -> 50173.469 | J68: =J61/(1+$C$48)^J$66 -> 107439.37 | K68: =K61/(1+$C$48)^K$66 -> 102689.69 | L68: =L61/(1+$C$48)^L$66 -> 96932.984 | M68: =M61/(1+$C$48)^M$66 -> 91345.177
B69: Terminal Value | H69: 0 | I69: =I62/(1+$C$48)^I$66 -> 0 | J69: =J62/(1+$C$48)^J$66 -> 0 | K69: =K62/(1+$C$48)^K$66 -> 0 | L69: =L62/(1+$C$48)^L$66 -> 0 | M69: =M62/(1+$C$48)^M$66 -> 1487391.1
B70: Total Cash Flow | H70: =SUM(H68:H69) -> 0 | I70: =SUM(I68:I69) -> 50173.469 | J70: =SUM(J68:J69) -> 107439.37 | K70: =SUM(K68:K69) -> 102689.69 | L70: =SUM(L68:L69) -> 96932.984 | M70: =SUM(M68:M69) -> 1578736.3
F73: ENTERPRISE VALUE | J73: ENTERPRISE VALUE
F74: Manual Method | H74: =SUM(I70:M70) -> 1935971.8 | J74: PV of Discrete | L74: =M74/$M$76 -> 0.23170828 | M74: =SUM(I68:M68) -> 448580.69
F75: XNPV Function 1 | H75: =XNPV(C48,H63:M63,H48:M48) -> 1935274.9 | J75: PV of Terminal | L75: =M75/$M$76 -> 0.76829172 | M75: =SUM(I69:M69) -> 1487391.1
J76: Enterprise Value | L76: =M76/$M$76 -> 1 | M76: =SUM(M74:M75) -> 1935971.8
F79: EQUITY VALUE | J79: EQUITY VALUE PER SHARE
F80: Enterprise Value | H80: =H75 -> 1935274.9 | J80: Equity Value | M80: =H82 -> 1989560.9
F81: Less: Net Debt | H81: =-Inputs!L107 -> 54286 | J81: Shares Outstanding | M81: =Inputs!F114 -> 14776
F82: Equity Value | H82: =SUM(H80:H81) -> 1989560.9 | J82: Equity Value | L82: ($/sh) | M82: =M80/M81 -> 134.64814
M85: The Enterprise Value from the XNPV Function is slightly different due to treatment of leap years.
B89: Discounted Cash Flow Schedule: Multiple Method
B91: All figures in USD millions unless stated
B92: =B45 -> Model Running: Base Case Drivers | H92: Valuation | I92: Discrete Forecast | N92: Term
H93: (YY-MM-DD) | I93: (YY-MM-DD) | J93: (YY-MM-DD) | K93: (YY-MM-DD) | L93: (YY-MM-DD) | M93: (YY-MM-DD) | N93: (YY-MM-DD)
B94: Terminal Multiple | C94: =Inputs!F117 -> 22 | F94: Fiscal Year End | H94: =Inputs!F103 -> 46121 | I94: =Inputs!F105 -> 46291 | J94: =EDATE(I94,12) -> 46656 | K94: =EDATE(J94,12) -> 47022 | L94: =EDATE(K94,12) -> 47387 | M94: =EDATE(L94,12) -> 47752 | N94: =EDATE(M94,12) -> 48117
B95: WACC | C95: =Inputs!L76 -> 0.08564409 | F95: Cash Flow Timing | H95: =H94 -> 46121 | I95: =Inputs!F104 -> 46291 | J95: =EDATE(I95,12) -> 46656 | K95: =EDATE(J95,12) -> 47022 | L95: =EDATE(K95,12) -> 47387 | M95: =EDATE(L95,12) -> 47752 | N95: =EDATE(M95,12) -> 48117
B97: Unlevered Free Cash Flow | I97: =I$31 -> 112360.89 | J97: =J$31 -> 121173.02 | K97: =K$31 -> 125735.19 | L97: =L$31 -> 128851.36 | M97: =M$31 -> 131822.8 | N97: =N$31 -> 130172.3
B98: EBITDA | N98: =N$17 -> 177027.97
B100: UNADJUSTED CASH FLOW
B101: Discrete Forecast | F101: Terminal | H101: 0 | I101: =I97 -> 112360.89 | J101: =J97 -> 121173.02 | K101: =K97 -> 125735.19 | L101: =L97 -> 128851.36 | M101: =M97 -> 131822.8 | N101: =N97 -> 130172.3
B102: Terminal Value 1 | F102: Adjustment | H102: 0 | I102: 0 | J102: 0 | K102: 0 | L102: 0 | M102: 0 | N102: =(N98*C94)/(1+C95)^F103 -> 3894615.4
B103: Total Cash Flow | F103: =YEARFRAC(N95,N94) -> 0 | H103: =SUM(H101:H102) -> 0 | I103: =SUM(I101:I102) -> 112360.89 | J103: =SUM(J101:J102) -> 121173.02 | K103: =SUM(K101:K102) -> 125735.19 | L103: =SUM(L101:L102) -> 128851.36 | M103: =SUM(M101:M102) -> 131822.8 | N103: =SUM(N101:N102) -> 4024787.7
B105: ADJUSTED CASH FLOW
B106: Partial Period Adjustment | H106: 0 | I106: =YEARFRAC(I94,H94) -> 0.46388889 | J106: =YEARFRAC(J94,I94) -> 1 | K106: =YEARFRAC(K94,J94) -> 1 | L106: =YEARFRAC(L94,K94) -> 1 | M106: =YEARFRAC(M94,L94) -> 1 | N106: =YEARFRAC(N94,M94) -> 1
B108: Discrete Forecast | H108: 0 | I108: =I101*I$106 -> 52122.97 | J108: =J101*J$106 -> 121173.02 | K108: =K101*K$106 -> 125735.19 | L108: =L101*L$106 -> 128851.36 | M108: =M101*M$106 -> 131822.8 | N108: =N101*N$106 -> 130172.3
B109: Terminal Value | H109: 0 | I109: =I102*I$106 -> 0 | J109: =J102*J$106 -> 0 | K109: =K102*K$106 -> 0 | L109: =L102*L$106 -> 0 | M109: =M102*M$106 -> 0 | N109: =N102*N$106 -> 3894615.4
B110: Total Cash Flow | H110: =SUM(H108:H109) -> 0 | I110: =SUM(I108:I109) -> 52122.97 | J110: =SUM(J108:J109) -> 121173.02 | K110: =SUM(K108:K109) -> 125735.19 | L110: =SUM(L108:L109) -> 128851.36 | M110: =SUM(M108:M109) -> 131822.8 | N110: =SUM(N108:N109) -> 4024787.7
B112: DISCOUNTED CASH FLOW
B113: Years for Discounting | H113: 0 | I113: =H113+YEARFRAC(H95,I95) -> 0.46388889 | J113: =I113+YEARFRAC(I95,J95) -> 1.4638889 | K113: =J113+YEARFRAC(J95,K95) -> 2.4638889 | L113: =K113+YEARFRAC(K95,L95) -> 3.4638889 | M113: =L113+YEARFRAC(L95,M95) -> 4.4638889 | N113: =M113+YEARFRAC(M95,N95) -> 5.4638889
B115: Discrete Forecast | H115: 0 | I115: =I108/(1+$C$95)^I$113 -> 50173.469 | J115: =J108/(1+$C$95)^J$113 -> 107439.37 | K115: =K108/(1+$C$95)^K$113 -> 102689.69 | L115: =L108/(1+$C$95)^L$113 -> 96932.984 | M115: =M108/(1+$C$95)^M$113 -> 91345.177 | N115: =N108/(1+$C$95)^N$113 -> 83085.681
B116: Terminal Value | H116: 0 | I116: =I109/(1+$C$95)^I$113 -> 0 | J116: =J109/(1+$C$95)^J$113 -> 0 | K116: =K109/(1+$C$95)^K$113 -> 0 | L116: =L109/(1+$C$95)^L$113 -> 0 | M116: =M109/(1+$C$95)^M$113 -> 0 | N116: =N109/(1+$C$95)^N$113 -> 2485834.4
B117: Total Cash Flow | H117: =SUM(H115:H116) -> 0 | I117: =SUM(I115:I116) -> 50173.469 | J117: =SUM(J115:J116) -> 107439.37 | K117: =SUM(K115:K116) -> 102689.69 | L117: =SUM(L115:L116) -> 96932.984 | M117: =SUM(M115:M116) -> 91345.177 | N117: =SUM(N115:N116) -> 2568920.1
F120: ENTERPRISE VALUE | J120: ENTERPRISE VALUE
F121: Manual Method | H121: =SUM(I117:N117) -> 3017500.8 | J121: PV of Discrete | L121: =M121/$M$123 -> 0.17619428 | M121: =SUM(I115:N115) -> 531666.37
F122: XNPV Function 2 | H122: =XNPV(C95,H110:N110,H95:N95) -> 3016394.8 | J122: PV of Terminal | L122: =M122/$M$123 -> 0.82380572 | M122: =SUM(I116:N116) -> 2485834.4
J123: Enterprise Value | L123: =M123/$M$123 -> 1 | M123: =SUM(M121:M122) -> 3017500.8
F126: EQUITY VALUE | J126: EQUITY VALUE PER SHARE
F127: Enterprise Value | H127: =H122 -> 3016394.8 | J127: Equity Value | M127: =H129 -> 3070680.8
F128: Less: Net Debt | H128: =-Inputs!L107 -> 54286 | J128: Shares Outstanding | M128: =Inputs!F114 -> 14776
F129: Equity Value | H129: =SUM(H127:H128) -> 3070680.8 | J129: Equity Value | L129: ($/sh) | M129: =M127/M128 -> 207.81543
M131: We have applied an LTM multiple to the EBITDA at the end of the terminal year to calculate the Terminal Value.
M132: The Enterprise Value from the XNPV Function is slightly different from the Manual Method due to treatment of leap years.
